cli_buddy/__init__.py
cli_buddy/__init__.pyi
cli_buddy/argument.py
cli_buddy/argument.pyi
cli_buddy/cli.py
cli_buddy/cli.pyi
cli_buddy/exceptions.py
cli_buddy/exceptions.pyi
cli_buddy-0.2.6.dist-info/LICENSE
cli_buddy-0.2.6.dist-info/METADATA
cli_buddy-0.2.6.dist-info/WHEEL
cli_buddy-0.2.6.dist-info/RECORD
