Metadata-Version: 2.1
Name: cli-buddy
Version: 0.2.6
Summary: The fastest, simplest way to create CLIs in Python
Home-page: https://github.com/jicruz96/cli-buddy
Keywords: data validation,dataclasses,validation,models,meta-programming
Author: J.I. Cruz
Author-email: hello@jicruz.com
Requires-Python: >=3.11,<4.0
Classifier: Intended Audience :: Developers
Classifier: License :: OSI Approved :: MIT License
Classifier: Programming Language :: Python :: 3
Classifier: Programming Language :: Python :: 3.11
Classifier: Programming Language :: Python :: 3.12
Requires-Dist: easydatamodel (>=0.3.2)
Project-URL: Repository, https://github.com/jicruz96/cli-buddy
